psychonaughtcrawler/__init__.py
psychonaughtcrawler/crawler.py
psychonaughtcrawler-1.0.1.data/scripts/run.py
utilities/__init__.py
utilities/crawler.py
psychonaughtcrawler-1.0.1.dist-info/LICENSE
psychonaughtcrawler-1.0.1.dist-info/METADATA
psychonaughtcrawler-1.0.1.dist-info/WHEEL
psychonaughtcrawler-1.0.1.dist-info/top_level.txt
psychonaughtcrawler-1.0.1.dist-info/RECORD
