Metadata-Version: 2.1
Name: psychonaughtcrawler
Version: 1.0.1
Summary: A crawler for PsychonaughtWiki wrote in python.
Home-page: https://github.com/BlakeBarnes00/PsychonaughtCrawler
Author: Ellis Barnes
Author-email: EllisBarnes00@gmail.com
License: This is free and unencumbered software released into the public domain.        
Project-URL: Bug Tracker, https://github.com/BlakeBarnes00/PsychonaughtCrawler/issues
Platform: UNKNOWN
Classifier: Development Status :: 1 - Planning
Classifier: Programming Language :: Python :: 3
Classifier: License :: OSI Approved :: The Unlicense (Unlicense)
Classifier: Operating System :: OS Independent
Classifier: Intended Audience :: Science/Research
Requires-Python: >=3.6
License-File: LICENSE
